rbac/__init__.py
rbac/acl.py
rbac/context.py
rbac/proxy.py
zato_ext_simple_rbac-0.1.1.dist-info/LICENSE
zato_ext_simple_rbac-0.1.1.dist-info/METADATA
zato_ext_simple_rbac-0.1.1.dist-info/WHEEL
zato_ext_simple_rbac-0.1.1.dist-info/top_level.txt
zato_ext_simple_rbac-0.1.1.dist-info/RECORD
